story/__init__.py
story/main.py
story/controllers/__init__.py
story/controllers/api/__init__.py
story/controllers/api/base.py
story/controllers/api/object.py
story/controllers/web/__init__.py
story/controllers/web/base.py
story/controllers/web/object.py
story/models/__init__.py
story/models/base.py
story/models/bucket.py
story/models/object.py
story/test/__init__.py
story/test/base.py
story_python-0.1.2.dist-info/METADATA
story_python-0.1.2.dist-info/WHEEL
story_python-0.1.2.dist-info/top_level.txt
story_python-0.1.2.dist-info/RECORD
